[
  {
    "title": "The Lost Island",
    "year": 2023,
    "genre": "Adventure",
    "duration": "1h 45m",
    "imageName": "movie_img_1",
    "posterName": "movie_poster_1",
    "isPremium": false
  },
  {
    "title": "Midnight Run",
    "year": 2024,
    "genre": "Thriller",
    "duration": "2h 5m",
    "imageName": "movie_img_2",
    "posterName": "movie_poster_2",
    "isPremium": true
  },
  {
    "title": "Shembe Ark - Pilot",
    "year": 2025,
    "genre": "Drama",
    "duration": "45m",
    "imageName": "series_img_1",
    "posterName": "series_poster_1",
    "isPremium": false
  }
]

